{
    "products": [
        {
            "buttonText": "10 Jan 2018",
            "name": "Addiction When Gambling Becomes A Problem",
            "imageSrc": "images/b1.jpg(1).webp",
            "description": "inappropriate behavior ipsum dolor sit amet, consectetur.",
            "latest-comment": {
                "likes": "15 Likes",
                "comment": "15 Comment"
            },
            "id": 1
        },
        {
            "buttonText": "10 Jan 2018",
            "name": "Addiction When Gambling Becomes A Problem",
            "imageSrc": "images/b1.jpg(1).webp",
            "description": "inappropriate behavior ipsum dolor sit amet, consectetur.",
            "latest-comment": {
                "likes": "15 Likes",
                "comment": "15 Comment"
            },
            "id": 2
        },
        {
            "buttonText": "10 Jan 2018",
            "name": "Addiction When Gambling Becomes A Problem",
            "imageSrc": "images/b1.jpg(1).webp",
            "description": "inappropriate behavior ipsum dolor sit amet, consectetur.",
            "latest-comment": {
                "likes": "15 Likes",
                "comment": "15 Comment"
            },
            "id": 3
        },
        {
            "buttonText": "10 Jan 2018",
            "name": "Addiction When Gambling Becomes A Problem",
            "imageSrc": "images/b1.jpg(1).webp",
            "description": "inappropriate behavior ipsum dolor sit amet, consectetur.",
            "latest-comment": {
                "likes": "15 Likes",
                "comment": "15 Comment"
            },
            "id": 4
        }
    ]
}